LICENSE
README.md
setup.py
grapheditdistance/__init__.py
grapheditdistance/base.py
grapheditdistance/consts.py
grapheditdistance/graph.py
grapheditdistance.egg-info/PKG-INFO
grapheditdistance.egg-info/SOURCES.txt
grapheditdistance.egg-info/dependency_links.txt
grapheditdistance.egg-info/requires.txt
grapheditdistance.egg-info/top_level.txt
grapheditdistance/distances/__init__.py
grapheditdistance/distances/base.py
grapheditdistance/distances/levenshtein.py
grapheditdistance/operators/__init__.py
grapheditdistance/operators/base.py
test/test_create_graph.py
test/test_levenshtein.py