Metadata-Version: 2.1
Name: grapheditdistance
Version: 0.1.1
Summary: A edit distance edition based on graphs.
Home-page: https://github.com/jmgomezsoriano/graph-edit-distance
Author: José Manuel Gómez Soriano
Author-email: jmgomez.soriano@gmail.com
License: LGPL2
Classifier: Programming Language :: Python :: 3
Classifier: License :: OSI Approved :: MIT License
Classifier: Operating System :: OS Independent
Requires-Python: >=3.7
License-File: LICENSE
Requires-Dist: networkx~=2.8.1
Requires-Dist: matplotlib~=3.5.2
Requires-Dist: numpy<1.27,>=1.22
Requires-Dist: multivaluedbtree~=0.0.1
Requires-Dist: mysmallutils~=1.0.18
